[
  {
    "id": "1",
    "question": "what is life?",
    "answers": [
      "life is a mystery",
      "rainbows and sunshine",
      "its a beach",
      "pain and suffering"
    ],
    "correctAnswer": "its a beach"
  },
  {
    "id": "2",
    "question": "who's got the funk?",
    "answers": ["I do", "Rick James", "Your mom", "Joe Rogan"],
    "correctAnswer": "I do"
  },
  {
    "id": "3",
    "question": "Worst NHL fanbase in the league?",
    "answers": ["Toronto", "Boston", "Washington", "Seattle"],
    "correctAnswer": "Toronto"
  },
  {
    "id": "4",
    "question": "When are you skiing?",
    "answers": ["Never", "Today", "Tomorrow", "Everyday!"],
    "correctAnswer": "Everyday!"
  }
]
